jupyter_formily/__init__.py
jupyter_formily/_contant.py
jupyter_formily/formily.py
jupyter_formily/toast.py
vendor/formily/dist/Formily.css
vendor/formily/dist/Formily.js
vendor/formily/dist/Toast.js
jupyter_formily-0.0.7.dist-info/LICENSE
jupyter_formily-0.0.7.dist-info/METADATA
jupyter_formily-0.0.7.dist-info/WHEEL
jupyter_formily-0.0.7.dist-info/RECORD
