Metadata-Version: 2.1
Name: jupyter-formily
Version: 0.0.7
Summary: Integrates fomily to jupyter notebook, which base on anywidget
Author: zllin
Author-email: mark@xmu.edu.cn
Requires-Python: >=3.8,<4.0
Classifier: Programming Language :: Python :: 3
Classifier: Programming Language :: Python :: 3.8
Classifier: Programming Language :: Python :: 3.9
Classifier: Programming Language :: Python :: 3.10
Classifier: Programming Language :: Python :: 3.11
Requires-Dist: anywidget[dev] (==0.7.0)
